systemathics/apis/__init__.py
systemathics/apis/helpers/channel_helpers.py
systemathics/apis/helpers/token_helpers.py
systemathics/apis/services/corporate_actions/v1/changes_pb2.py
systemathics/apis/services/corporate_actions/v1/changes_pb2_grpc.py
systemathics/apis/services/corporate_actions/v1/dividends_pb2.py
systemathics/apis/services/corporate_actions/v1/dividends_pb2_grpc.py
systemathics/apis/services/corporate_actions/v1/splits_pb2.py
systemathics/apis/services/corporate_actions/v1/splits_pb2_grpc.py
systemathics/apis/services/daily/v1/daily_bars_pb2.py
systemathics/apis/services/daily/v1/daily_bars_pb2_grpc.py
systemathics/apis/services/daily/v1/daily_calendars_pb2.py
systemathics/apis/services/daily/v1/daily_calendars_pb2_grpc.py
systemathics/apis/services/daily/v1/daily_greeks_pb2.py
systemathics/apis/services/daily/v1/daily_greeks_pb2_grpc.py
systemathics/apis/services/daily/v1/daily_implied_volatility_pb2.py
systemathics/apis/services/daily/v1/daily_implied_volatility_pb2_grpc.py
systemathics/apis/services/daily/v1/daily_market_data_pb2.py
systemathics/apis/services/daily/v1/daily_market_data_pb2_grpc.py
systemathics/apis/services/daily/v1/daily_open_interest_pb2.py
systemathics/apis/services/daily/v1/daily_open_interest_pb2_grpc.py
systemathics/apis/services/daily/v1/daily_prices_pb2.py
systemathics/apis/services/daily/v1/daily_prices_pb2_grpc.py
systemathics/apis/services/daily/v1/daily_settlement_pb2.py
systemathics/apis/services/daily/v1/daily_settlement_pb2_grpc.py
systemathics/apis/services/daily/v1/daily_vwap_pb2.py
systemathics/apis/services/daily/v1/daily_vwap_pb2_grpc.py
systemathics/apis/services/daily_analytics/v1/daily_bollinger_pb2.py
systemathics/apis/services/daily_analytics/v1/daily_bollinger_pb2_grpc.py
systemathics/apis/services/daily_analytics/v1/daily_cma_pb2.py
systemathics/apis/services/daily_analytics/v1/daily_cma_pb2_grpc.py
systemathics/apis/services/daily_analytics/v1/daily_ema_pb2.py
systemathics.apis-2.40.0.dist-info/LICENSE
systemathics.apis-2.40.0.dist-info/METADATA
systemathics.apis-2.40.0.dist-info/WHEEL
systemathics.apis-2.40.0.dist-info/top_level.txt
systemathics.apis-2.40.0.dist-info/RECORD
