Metadata-Version: 2.1
Name: systemathics.apis
Version: 2.40.0
Summary: Grpc stub for Systemathics API.
Author-email: Systemathics <contact@systemathics.com>
License: MIT License
Project-URL: Homepage, https://ganymede.cloud
Project-URL: Bug Tracker, https://github.com/systemathics/sdk-python/issues
Project-URL: Documentation, https://ganymede.cloud/api-documentation.html
Classifier: Programming Language :: Python :: 3
Classifier: License :: OSI Approved :: MIT License
Classifier: Operating System :: OS Independent
Classifier: Intended Audience :: Developers
Classifier: Intended Audience :: Information Technology
Classifier: Intended Audience :: Science/Research
Requires-Python: >=3.7
License-File: LICENSE
Requires-Dist: googleapis-common-protos
